setup.py
gaia_test_first/__init__.py
gaia_test_first/main.py
gaia_test_first.egg-info/PKG-INFO
gaia_test_first.egg-info/SOURCES.txt
gaia_test_first.egg-info/dependency_links.txt
gaia_test_first.egg-info/requires.txt
gaia_test_first.egg-info/top_level.txt