Metadata-Version: 2.1
Name: gaia-test-first
Version: 0.0.1
Summary: gaia test description
Home-page: UNKNOWN
Author: footprint dev
Author-email: github@footprint.network
License: MIT
Platform: UNKNOWN
Classifier: License :: OSI Approved :: MIT License
Classifier: Programming Language :: Python
Classifier: Programming Language :: Python :: 3
Classifier: Programming Language :: Python :: 3.6
Classifier: Programming Language :: Python :: Implementation :: CPython
Classifier: Programming Language :: Python :: Implementation :: PyPy
Requires-Python: >=3.6.0
